hemnes/__init__.py
hemnes/hemnes.py
hemnes/helpers/Logger.py
hemnes/helpers/Options.py
hemnes/helpers/PageFetcher.py
hemnes/helpers/Product.py
hemnes/helpers/__init__.py
hemnes/helpers/find_element.py
hemnes/helpers/scrape.py
hemnes/helpers/url_generator.py
test/__init__.py
test/test_integrated.py
test/test_isolated.py
hemnes-1.2.2.dist-info/LICENSE
hemnes-1.2.2.dist-info/METADATA
hemnes-1.2.2.dist-info/WHEEL
hemnes-1.2.2.dist-info/top_level.txt
hemnes-1.2.2.dist-info/RECORD
