Metadata-Version: 2.1
Name: hemnes
Version: 1.2.2
Summary: Ikea product scraper
Home-page: https://github.com/sayeefrmoyen/hemnes
Author: Sayeef Moyen
Author-email: develop.sayeefrm@gmail.com
License: UNKNOWN
Keywords: scraping ikea ikea-scraping python3 beautifulsoup,beautiful-soup
Platform: UNKNOWN
Classifier: Programming Language :: Python :: 3
Classifier: License :: OSI Approved :: MIT License
Classifier: Operating System :: OS Independent
Requires-Python: >=3
Requires-Dist: selenium
Requires-Dist: bs4
Requires-Dist: pytest
